{
  "globalStyle": {
    "navigationBarBackgroundColor": "#faf8f5",
    "navigationBarTextStyle": "black",
    "backgroundColor": "#faf8f5"
  },
  "pages": [
    {
      "path": "pages/login/index",
      "style": {
        "navigationBarTitleText": "登录",
        "navigationBarBackgroundColor": "#fef9f3",
        "navigationStyle": "custom"
      }
    },
    {
      "path": "pages/agreement/user",
      "style": { "navigationBarTitleText": "用户协议" }
    },
    {
      "path": "pages/agreement/privacy",
      "style": { "navigationBarTitleText": "隐私政策" }
    },
    {
      "path": "pages/index/index",
      "style": {
        "navigationBarTitleText": "智康AI",
        "navigationBarBackgroundColor": "#faf8f5",
        "navigationBarTextStyle": "black"
      }
    },
    {
      "path": "pages/data/index",
      "style": { "navigationBarTitleText": "分析" }
    },
    {
      "path": "pages/data/export",
      "style": { "navigationBarTitleText": "导出周报" }
    },
    {
      "path": "pages/ai/index",
      "style": { "navigationBarTitleText": "智康AI" }
    },
    {
      "path": "pages/goal/index",
      "style": { "navigationBarTitleText": "目标" }
    },
    {
      "path": "pages/goal/add",
      "style": { "navigationBarTitleText": "添加目标" }
    },
    {
      "path": "pages/reminders/index",
      "style": { "navigationBarTitleText": "提醒" }
    },
    {
      "path": "pages/reminders/add",
      "style": { "navigationBarTitleText": "新增提醒" }
    },
    {
      "path": "pages/medications/index",
      "style": { "navigationBarTitleText": "药物管理" }
    },
    {
      "path": "pages/medications/add",
      "style": { "navigationBarTitleText": "添加药物" }
    },
    {
      "path": "pages/medications/checkin",
      "style": { "navigationBarTitleText": "用药打卡" }
    },
    {
      "path": "pages/medications/detail",
      "style": { "navigationBarTitleText": "药物详情" }
    },
    {
      "path": "pages/family/index",
      "style": { "navigationBarTitleText": "家庭成员" }
    },
    {
      "path": "pages/family/invite",
      "style": { "navigationBarTitleText": "邀请家人" }
    },
    {
      "path": "pages/family/add",
      "style": { "navigationBarTitleText": "添加家庭成员" }
    },
    {
      "path": "pages/period/index",
      "style": { "navigationBarTitleText": "经期记录" }
    },
    {
      "path": "pages/privacy/index",
      "style": { "navigationBarTitleText": "授权与隐私" }
    },
    {
      "path": "pages/record/index",
      "style": { "navigationBarTitleText": "快速记录" }
    },
    {
      "path": "pages/profile/index",
      "style": { "navigationBarTitleText": "我的" }
    }
  ],
  "tabBar": {
    "custom": false,
    "color": "#94a3b8",
    "selectedColor": "#2563eb",
    "backgroundColor": "#ffffff",
    "borderStyle": "black",
    "list": [
      {
        "pagePath": "pages/index/index",
        "text": "首页",
        "iconPath": "static/tabbar/home.png",
        "selectedIconPath": "static/tabbar/home-active.png"
      },
      {
        "pagePath": "pages/data/index",
        "text": "分析",
        "iconPath": "static/tabbar/data.png",
        "selectedIconPath": "static/tabbar/data-active.png"
      },
      {
        "pagePath": "pages/ai/index",
        "text": "AI",
        "iconPath": "static/tabbar/robot.png",
        "selectedIconPath": "static/tabbar/robot-active.png"
      },
      {
        "pagePath": "pages/profile/index",
        "text": "我的",
        "iconPath": "static/tabbar/profile.png",
        "selectedIconPath": "static/tabbar/profile-active.png"
      }
    ]
  }
}
